[  
  {
    "title": "Lingdong Huang",
    "images": [
      {
        "url": "media/lingdong.png",
        "size": "140%",
        "position": "50% 35%"
      }
    ],
    "description": "Who made all the other stuff on this site...",
    "links": {
      "Github": "https://github.com/LingDong-/",
      "Vimeo": "https://vimeo.com/user48479503",
      "Itch.io": "https://lingdonh.itch.io/",
      "Résumé": "https://cdn.glitch.com/6df32ef1-b99f-4c8b-a119-58c1ef7b41bf%2Flingdonh-resume.pdf?v=1566371622525"
    },
    "medium": [
      ""
    ],
    "date": {
      "month": 7,
      "year": 1997
    }
  },{
    "title": "Hermit",
    "images": [
      {
        "url": "media/hermit.gif",
        "size": "100%",
        "position": "50% 50%"
      }
    ],
    "description": "Interactive procedurally generated landscapes.",
    "links": {
      "Youtube": "https://www.youtube.com/watch?v=mPYeTJd8klQ",
      "Github": "https://github.com/LingDong-/Hermit"
    },
    "medium": [
      "Python"
    ],
    "date": {
      "month": 11,
      "year": 2015
    }
  },
  {
    "title": "Fauna of Sloogia",
    "images": [
      {
        "url": "media/sloogia.png",
        "size": "200%",
        "position": "50% 40%"
      }
    ],
    "description": "Book of generated imaginary creatures.",
    "links": {
      "Blurb": "https://www.blurb.com/books/7429507-fauna-of-sloogia-generative-creatures",
      "PDF": "https://cmuems.com/2016/60212/wp-content/uploads/2016/12/MuKJ8N.pdf",
      "Documentation": "./documentation?https://dl.dropbox.com/s/28k0hv421ofk9pz/fauna-of-sloogia.md"
    },
    "medium": [
      "Processing",
      "Basil.js"
    ],
    "date": {
      "month": 10,
      "year": 2016
    }
  },
  {
    "title": "Plotter Landscapes",
    "images": [
      {
        "url": "media/plotter.jpg",
        "size": "150%",
        "position": "50% 50%"
      }
    ],
    "description": "Generative landscapes for plotters.",
    "links": {
      "Code & Documentation": "./documentation?https://dl.dropbox.com/s/tpir3t6upd4zyvn/plotter-landscapes.md"
    },
    "medium": [
      "Processing",
      "Axidraw"
    ],
    "date": {
      "month": 9,
      "year": 2016
    }
  },
  {
    "title": "Face-Powered Shooter",
    "images": [
      {
        "url": "media/fps.gif",
        "size": "130%",
        "position": "50% 50%"
      }
    ],
    "description": "First person shooter controlled by facial expressions.",
    "links": {
      "Vimeo": "https://vimeo.com/187285292",
      "Code & Documentation": "./documentation?https://dl.dropbox.com/s/04i9dtxnz9h0rzm/face-powered-shooter.md?dl=0"
    },
    "medium": [
      "Processing",
      "FaceOSC"
    ],
    "date": {
      "month": 10,
      "year": 2016
    }
  },
  {
    "title": "The Toilet Paper Printer",
    "images": [
      {
        "url": "media/printer.png",
        "size": "400%",
        "position": "50% 10%"
      }
    ],
    "description": "DIY plotter made with cardboard and straws.",
    "links": {
      "Vimeo": "https://vimeo.com/192161788",
      "Documentation": "./documentation?https://dl.dropbox.com/s/474wex4gfi9no27/toilet-paper-printer.md"
    },
    "medium": [
      "Processing",
      "Bash",
      "littleBits"
    ],
    "date": {
      "month": 10,
      "year": 2016
    }
  },
  {
    "title": "Trashscape",
    "images": [
      {
        "url": "media/trashscape.png",
        "size": "200%",
        "position": "0% 80%"
      }
    ],
    "description": "Aman's portrait seen through his trash.",
    "links": {
      "Vimeo": "https://vimeo.com/204271262",
      "Doc": "./documentation?https://dl.dropbox.com/s/4d8hhvtaiaemb8j/trashscape.md",
      "Mac Download": "https://drive.google.com/file/d/0B1w_KJh9VUO7NERpSmJmWWxISHM/view?usp=sharing"
    },
    "medium": [
      "C#",
      "Unity",
      "PhotoScan Pro"
    ],
    "date": {
      "month": 2,
      "year": 2017
    }
  },
  {
    "title": "photoBarcoder",
    "images": [
      {
        "url": "media/photobarcoder.bmp",
        "size": "130%",
        "position": "50% 50%"
      }
    ],
    "description": "Mobile app for turning photos into scannable barcodes.",
    "links": {
      "Vimeo": "https://vimeo.com/207668010",
      "Documentation": "./documentation?https://dl.dropbox.com/s/7h5ytkwdmz4z0i2/photo-barcoder.md"
    },
    "medium": [
      "Python",
      "Processing for Android"
    ],
    "date": {
      "month": 3,
      "year": 2017
    }
  },
  {
    "title": "Image Sequencer",
    "images": [
      {
        "url": "media/imgseq.png",
        "size": "120%",
        "position": "50% 50%"
      }
    ],
    "description": "Programmatically sequence crowd-sourced images into gifs.",
    "links": {
      "Documentation": "./documentation?https://dl.dropbox.com/s/0feqbm69w68ldoa/image-sequencer.md"
    },
    "medium": [
      "Python",
      "OpenCV"
    ],
    "date": {
      "month": 5,
      "year": 2017
    }
  },
  {
    "title": "Loopy Mocap Skin",
    "images": [
      {
        "url": "media/mocap.png",
        "size": "150%",
        "position": "10% 50%"
      }
    ],
    "description": "Decorative skin for motion capture data.",
    "links": {
      "Vimeo": "https://vimeo.com/191059977",
      "Code & Documentation": "./documentation?https://dl.dropbox.com/s/wuagqc1llbe9jaa/loopy-mocap-skin.md"
    },
    "medium": [
      "Processing"
    ],
    "date": {
      "month": 11,
      "year": 2016
    }
  },
  {
    "title": "Gen-a-city",
    "images": [
      {
        "url": "media/genacity.jpg",
        "size": "150%",
        "position": "0% 50%"
      }
    ],
    "description": "Procedurally generated satellite image of cities.",
    "links": {
      "Play Online": "https://www.andrew.cmu.edu/user/lingdonh/Gen-a-city/"
    },
    "medium": [
      "Javascript"
    ],
    "date": {
      "month": 9,
      "year": 2015
    }
  },{
    "title": "Estoc",
    "images": [
      {
        "url": "media/estoc.gif",
        "size": "200%",
        "position": "50% 80%"
      }
    ],
    "description": "Competitive swordplay featuring dismemberment.",
    "links": {
      "Steam": "https://steamcommunity.com/sharedfiles/filedetails/?id=439698626",
      "Youtube": "https://www.youtube.com/watch?v=oXyUAyj3Go4"
    },
    "medium": [
      "Lua",
      "Love2D"
    ],
    "date": {
      "month": 7,
      "year": 2015
    }
  },{
    "title": "Light Bearer",
    "images": [
      {
        "url": "media/lightbearer.gif",
        "size": "150%",
        "position": "50% 80%"
      }
    ],
    "description": "A tiny game about light and darkness.",
    "links": {
      "Itch.io": "https://lingdonh.itch.io/light-bearer"
    },
    "medium": [
      "p5.js"
    ],
    "date": {
      "month": 12,
      "year": 2015
    }
  },{
    "title": "Ci-ren",
    "images": [
      {
        "url": "media/ciren.png",
        "size": "280%",
        "position": "50% 45%"
      }
    ],
    "description": "Generative Chinese poetry.",
    "links": {
      "Github": "https://github.com/LingDong-/ci-ren",
      "Play Online": "https://lingdong-.github.io/ci-ren/"
    },
    "medium": [
      "Python",
      "Javascript"
    ],
    "date": {
      "month": 8,
      "year": 2016
    }
  },{
    "title": "imgmarkov",
    "images": [
      {
        "url": "https://github.com/memegen/imgmarkov/raw/master/screenshots/1.png?raw=true",
        "size": "100%",
        "position": "80% 0%"
      }
    ],
    "description": "Dreams up images using multi-dimensional markov chains.",
    "links": {
      "Github": "https://github.com/memegen/imgmarkov"
    },
    "medium": [
      "Python"
    ],
    "date": {
      "month": 12,
      "year": 2016
    }
  },{
    "title": "linedraw",
    "images": [
      {
        "url": "https://github.com/LingDong-/linedraw/raw/master/screenshots/1.png?raw=true",
        "size": "220%",
        "position": "70% 10%"
      }
    ],
    "description": "Convert images to vectorized line drawings for plotters.",
    "links": {
      "Github": "https://github.com/LingDong-/linedraw"
    },
    "medium": [
      "Python",
      "OpenCV"
    ],
    "date": {
      "month": 12,
      "year": 2016
    }
  },{
    "title": "Better Horses",
    "images": [
      {
        "url": "media/betterhorses.png",
        "size": "180%",
        "position": "40% 65%"
      }
    ],
    "description": "Multiplayer Generative Beast Racing & Betting.",
    "links": {
      "Itch.io": "https://lingdonh.itch.io/better-horses"
    },
    "medium": [
      "C#",
      "Unity"
    ],
    "date": {
      "month": 11,
      "year": 2017
    }
  },{
    "title": "Normal Human Face Simulator",
    "images": [
      {
        "url": "media/nhfs.png",
        "size": "100%",
        "position": "50% 40%"
      }
    ],
    "description": "Local 2-player face-biting simulation.",
    "links": {
      "Itch.io": "https://lingdonh.itch.io/normal-human-face-simulator"
    },
    "medium": [
      "Lua",
      "Love2D"
    ],
    "date": {
      "month": 11,
      "year": 2017
    }
  },{
    "title": "{Shan, Shui}*",
    "images": [
      {
        "url": "media/shanshui.jpg",
        "size": "180%",
        "position": "40% 60%"
      }
    ],
    "description": "Infinite procedurally generated Chinese landscape painting.",
    "links": {
      "Github": "https://github.com/LingDong-/shan-shui-inf",
      "Play Online": "https://lingdong-.github.io/shan-shui-inf"
    },
    "medium": [
      "Javascript"
    ],
    "date": {
      "month": 2,
      "year": 2018
    }
  },{
    "title": "nonflowers",
    "images": [
      {
        "url": "https://github.com/LingDong-/nonflowers/raw/master/screenshots/screen01.jpg",
        "size": "700%",
        "position": "10% 10%"
      }
    ],
    "description": "Procedurally generated paintings of nonexistent flowers.",
    "links": {
      "Github": "https://github.com/LingDong-/nonflowers",
      "Play Online": "https://lingdong-.github.io/nonflowers/",
      "Doc": "https://drive.google.com/file/d/1g1gVmRKdn4He0fgavvKt54tb6HmMYANU/view"
    },
    "medium": [
      "Javascript"
    ],
    "date": {
      "month": 2,
      "year": 2018
    }
  },{
    "title": "Prophesy of Mind",
    "images": [
      {
        "url": "media/pom.jpg",
        "size": "100%",
        "position": "10% 10%"
      }
    ],
    "description": "Experimental film about a dream.",
    "links": {
      "Vimeo": "https://vimeo.com/165344992"
    },
    "medium": [
      "Adobe Premiere Pro"
    ],
    "date": {
      "month": 5,
      "year": 2016
    }
  },{
    "title": "Human Powered Computers",
    "images": [
      {
        "url": "media/tile.png",
        "size": "120%",
        "position": "0% 0%"
      }
    ],
    "description": "Seamlessly tilable texture featuring human powered computers.",
    "links": {
      "Documentation": "https://cdn.glitch.com/6df32ef1-b99f-4c8b-a119-58c1ef7b41bf%2Fimg-tile.png?1543713069304"
    },
    "medium": [
      "Screen print"
    ],
    "date": {
      "month": 9,
      "year": 2017
    }
  },{
    "title": "Pix2Pix Cities",
    "images": [
      {
        "url": "media/pix2pixcity.jpg",
        "size": "100%",
        "position": "40% 0%"
      }
    ],
    "description": "Procedurally generated cities with photorealistic rendering by Pix2Pix.",
    "links": {
      "Github": "https://github.com/DerTarchin/Pix2Pix-Generative-Cities",
      "Youtube": "https://www.youtube.com/watch?v=-P_Sfl4e1xo"
    },
    "medium": [
      "C#", "Unity", "Python"
    ],
    "date": {
      "month": 5,
      "year": 2018
    }
  },{
    "title": "edges2calligraphy",
    "images": [
      {
        "url": "media/e2c.png",
        "size": "155%",
        "position": "30% 55%"
      }
    ],
    "description": "Turn your scribbles into Chinese calligraphy.",
    "links": {
      "Github": "https://github.com/LingDong-/edges2calligraphy",
      "Play Online": "https://lingdong-.github.io/edges2calligraphy/"
    },
    "medium": [
      "Javascript", "Python"
    ],
    "date": {
      "month": 4,
      "year": 2018
    }
  },{
    "title": "Recursive Radical Packing Language",
    "images": [
      {
        "url": "https://github.com/LingDong-/rrpl/raw/master/doc/screen000-1.png",
        "size": "100%",
        "position": "30% 55%"
      }
    ],
    "description": "A new method for describing and visualizing Chinese characters.",
    "links": {
      "Github": "https://github.com/LingDong-/rrpl",
      "Play Online": "https://chinese-radical-vis.glitch.me"
    },
    "medium": [
      "Javascript", "Python"
    ],
    "date": {
      "month": 10,
      "year": 2018
    }
  },{
    "title": "Instruction Manual - Stool",
    "images": [
      {
        "url": "media/stool.png",
        "size": "100%",
        "position": "-50% 50%"
      }
    ],
    "description": "Manual for advanced multi-directional human seating device",
    "links": {
      "PDF": "https://drive.google.com/file/d/15M94-hDETjHW4BqbujPpiFcxn4GTUNes/view?usp=sharing",
      "Documentation": "https://drive.google.com/file/d/1_wZQRgoSYkjwTlrCFNN76z_mTvEqHeOW/view?usp=sharing"
    },
    "medium": [
      "Digital print"
    ],
    "date": {
      "month": 11,
      "year": 2017
    }
  },{
    "title": "Legend of Wrong Mountain",
    "images": [
      {
        "url": "media/lowm.png",
        "size": "100%",
        "position": "40% 50%"
      }
    ],
    "description": "Full generation of traditional Chinese opera using multiple machine learning algorithms",
    "links": {
      "Youtube": "https://www.youtube.com/watch?v=QPdb28h4qjc",
      "NIPS Paper": "https://nips2018creativity.github.io/doc/legend_of_wrong_mountain.pdf"
    },
    "medium": [
      "Python"
    ],
    "date": {
      "month": 5,
      "year": 2018
    }
  },{
    "title": "age2death",
    "images": [
      {
        "url": "media/a2d.png",
        "size": "120%",
        "position": "50% 50%"
      }
    ],
    "description": "A mirror to watch yourself age to death (online)",
    "links": {
      "Play Online": "https://age2death.glitch.me",
      "Vimeo": "https://vimeo.com/315573733",
      "Doc": "https://golancourses.net/2019/ngdon/01/30/ngdon-mask/"
    },
    "medium": [
      "Javascript", "three.js", "handsfree.js"
    ],
    "date": {
      "month": 2,
      "year": 2019
    }
  },{
    "title": "doodle-place",
    "images": [
      {
        "url": "media/doodle.png",
        "size": "100%",
        "position": "50% 20%"
      }
    ],
    "description": "A virtual world inhabited by user-submitted, computationally-animated doodles",
    "links": {
      "Play Online": "https://doodle-place.glitch.me",
      "Documentation": "https://golancourses.net/2019/ngdon/03/05/ngdon-drawingsoftware/"
    },
    "medium": [
      "Javascript", "three.js", "OpenCV.js", "tensorflow.js", "sqlite"
    ],
    "date": {
      "month": 3,
      "year": 2019
    }
  },{
    "title": "emojia",
    "images": [
      {
        "url": "media/emojia.png",
        "size": "100%",
        "position": "50% 50%"
      }
    ],
    "description": "An online multiplayer world made entirely of emojis",
    "links": {
      "Play Online": "https://emojia.glitch.me",
      "Documentation": "https://golancourses.net/2019/ngdon/04/10/ngdon-telematic/"
    },
    "medium": [
      "Javascript", "socket.io"
    ],
    "date": {
      "month": 4,
      "year": 2019
    }
  },{
    "title": "wenyan-lang (文言)",
    "images": [
      {
        "url": "https://github.com/wenyan-lang/wenyan/raw/master/screenshots/screenshot01.png",
        "size": "120%",
        "position": "50% 50%"
      }
    ],
    "description": "A programming language in Classical Chinese",
    "links": {
      "Website": "https://wy-lang.org/",
      "Github": "https://github.com/wenyan-lang/wenyan",
      "Book": "https://github.com/wenyan-lang/book"
    },
    "medium": [
      "TypeScript"
    ],
    "date": {
      "month": 12,
      "year": 2019
    }
  },{
    "title": "QIJI Font",
    "images": [
      {
        "url": "https://github.com/LingDong-/qiji-font/raw/master/screenshots/screenshot001.png",
        "size": "200%",
        "position": "50% 50%"
      }
    ],
    "description": "Typeface extracted from Ming Dynasty woodblock printed books",
    "links": {
      "Website": "https://qiji-font.netlify.app/",
      "Github": "hhttps://github.com/LingDong-/qiji-font"
    },
    "medium": [
      "Python","Javascript","OpenCV"
    ],
    "date": {
      "month": 2,
      "year": 2020
    }
  }

]